boardx/__init__.py
boardx-0.1.4.dist-info/LICENSE
boardx-0.1.4.dist-info/WHEEL
boardx-0.1.4.dist-info/METADATA
boardx-0.1.4.dist-info/RECORD
