Metadata-Version: 2.1
Name: boardx
Version: 0.1.4
Summary: Dive into Board.
Author-email: xinetzone <735613050@qq.com>
Maintainer-email: xinetzone <735613050@qq.com>
Requires-Python: >=3.8
Classifier: License :: OSI Approved :: Apache Software License
Requires-Dist: sphinx>=4.5
Requires-Dist: invoke
Requires-Dist: xyzstyle
Requires-Dist: sphinx-book-theme>=0.1.6 ; extra == "doc"
Requires-Dist: ablog ; extra == "doc"
Requires-Dist: myst-nb ; extra == "doc"
Requires-Dist: sphinx-thebe ; extra == "doc"
Requires-Dist: sphinx-copybutton ; extra == "doc"
Requires-Dist: sphinx-comments ; extra == "doc"
Requires-Dist: plotly ; extra == "doc"
Requires-Dist: pandas ; extra == "doc"
Requires-Dist: matplotlib ; extra == "doc"
Requires-Dist: sphinxcontrib-mermaid ; extra == "doc"
Requires-Dist: sphinx-panels ; extra == "doc"
Requires-Dist: sphinx-inline-tabs ; extra == "doc"
Requires-Dist: sphinx-automodapi ; extra == "doc"
Project-URL: Home, https://github.com/xinetzone/d2b
Provides-Extra: doc
